odoo/addons/account_fiscal_month/README.rst
odoo/addons/account_fiscal_month/__init__.py
odoo/addons/account_fiscal_month/__manifest__.py
odoo/addons/account_fiscal_month/data/date_range_type.xml
odoo/addons/account_fiscal_month/i18n/account_fiscal_month.pot
odoo/addons/account_fiscal_month/i18n/de.po
odoo/addons/account_fiscal_month/i18n/el_GR.po
odoo/addons/account_fiscal_month/i18n/es.po
odoo/addons/account_fiscal_month/i18n/es_EC.po
odoo/addons/account_fiscal_month/i18n/fi.po
odoo/addons/account_fiscal_month/i18n/fr.po
odoo/addons/account_fiscal_month/i18n/hr.po
odoo/addons/account_fiscal_month/i18n/hr_HR.po
odoo/addons/account_fiscal_month/i18n/it.po
odoo/addons/account_fiscal_month/i18n/lt.po
odoo/addons/account_fiscal_month/i18n/nl.po
odoo/addons/account_fiscal_month/i18n/nl_NL.po
odoo/addons/account_fiscal_month/i18n/pt.po
odoo/addons/account_fiscal_month/i18n/pt_BR.po
odoo/addons/account_fiscal_month/i18n/sk.po
odoo/addons/account_fiscal_month/i18n/sl.po
odoo/addons/account_fiscal_month/i18n/tr.po
odoo/addons/account_fiscal_month/i18n/tr_TR.po
odoo/addons/account_fiscal_month/models/__init__.py
odoo/addons/account_fiscal_month/models/date_range_type.py
odoo/addons/account_fiscal_month/models/res_company.py
odoo/addons/account_fiscal_month/readme/CONTRIBUTORS.rst
odoo/addons/account_fiscal_month/readme/DESCRIPTION.rst
odoo/addons/account_fiscal_month/static/description/icon.png
odoo/addons/account_fiscal_month/static/description/index.html
odoo/addons/account_fiscal_month/tests/__init__.py
odoo/addons/account_fiscal_month/tests/test_account_fiscal_month.py
odoo/addons/account_fiscal_month/views/date_range_type.xml
odoo13_addon_account_fiscal_month-13.0.1.0.1.dev6.dist-info/METADATA
odoo13_addon_account_fiscal_month-13.0.1.0.1.dev6.dist-info/WHEEL
odoo13_addon_account_fiscal_month-13.0.1.0.1.dev6.dist-info/top_level.txt
odoo13_addon_account_fiscal_month-13.0.1.0.1.dev6.dist-info/RECORD
